audiotranser/README.MD
audiotranser/__init__.py
audiotranser/requirements.txt
audiotranser/thirdparty.json
audiotranser/blasx64/SDL2.dll
audiotranser/blasx64/bench.exe
audiotranser/blasx64/libopenblas.dll
audiotranser/blasx64/main.exe
audiotranser/blasx64/quantize.exe
audiotranser/blasx64/whisper.dll
audiotranser/x64/SDL2.dll
audiotranser/x64/bench.exe
audiotranser/x64/main.exe
audiotranser/x64/quantize.exe
audiotranser/x64/whisper.dll
audiotranser-0.10.dist-info/LICENSE.rst
audiotranser-0.10.dist-info/METADATA
audiotranser-0.10.dist-info/WHEEL
audiotranser-0.10.dist-info/top_level.txt
audiotranser-0.10.dist-info/RECORD
