Metadata-Version: 2.1
Name: audiotranser
Version: 0.10
Summary: Transcribes audio files
Home-page: https://github.com/hansalemaos/audiotranser
Author: Johannes Fischer
Author-email: aulasparticularesdealemaosp@gmail.com
License: MIT
Keywords: audio,Transcribe
Classifier: Development Status :: 4 - Beta
Classifier: Programming Language :: Python :: 3 :: Only
Classifier: Programming Language :: Python :: 3.10
Classifier: Topic :: Software Development :: Libraries :: Python Modules
Classifier: Topic :: Utilities
License-File: LICENSE.rst
Requires-Dist: huggingface-hub
Requires-Dist: pandas
Requires-Dist: pydub
Requires-Dist: touchtouch
